slimer/__init__.py
slimer/__version__.py
slimer/constants.py
slimer/main.py
slimer-1.0.6.dist-info/LICENSE
slimer-1.0.6.dist-info/METADATA
slimer-1.0.6.dist-info/WHEEL
slimer-1.0.6.dist-info/entry_points.txt
slimer-1.0.6.dist-info/RECORD
