Metadata-Version: 2.1
Name: slimer
Version: 1.0.6
Summary: Slimer reads your folder structure and file contents to transform it into a concise, readable string overview
License: MIT
Author: Ben Villiere
Requires-Python: >=3.9,<4.0
Classifier: License :: OSI Approved :: MIT License
Classifier: Programming Language :: Python :: 3
Classifier: Programming Language :: Python :: 3.9
Classifier: Programming Language :: Python :: 3.10
Classifier: Programming Language :: Python :: 3.11
Requires-Dist: pyperclip (>=1.8.2,<2.0.0)
